pycomponents/__init__.py
pycomponents/bom.py
pycomponents/cli.py
pycomponents/components.py
pycomponents/constants.py
pycomponents/cve_search/__init__.py
pycomponents/cve_search/schemas.py
pycomponents/exceptions.py
pycomponents/osv/__init__.py
pycomponents/osv/schemas.py
pycomponents/output.py
pycomponents/processes.py
pycomponents/service.py
pycomponents/settings.py
pycomponents/site_packages.py
pycomponents/utils.py
pycomponents/vulnerability.py
py_sbom_components-0.2.1.dist-info/entry_points.txt
py_sbom_components-0.2.1.dist-info/LICENSE
py_sbom_components-0.2.1.dist-info/WHEEL
py_sbom_components-0.2.1.dist-info/METADATA
py_sbom_components-0.2.1.dist-info/RECORD
