Metadata-Version: 2.1
Name: py-sbom-components
Version: 0.2.1
Summary: An experimental tool to generate CycloneDX BOM from running Python processes
Home-page: https://github.com/ninoseki/pycomponents
Author: Manabu Niseki
Author-email: manabu.niseki@gmail.com
Requires-Python: >=3.8,<4.0
Classifier: Programming Language :: Python :: 3
Classifier: Programming Language :: Python :: 3.10
Classifier: Programming Language :: Python :: 3.8
Classifier: Programming Language :: Python :: 3.9
Requires-Dist: arrow (>=1.2.2,<2.0.0)
Requires-Dist: cachetools (>=5.2.0,<6.0.0)
Requires-Dist: cyclonedx-python-lib (>=2.7.1,<3.0.0)
Requires-Dist: environs (>=9.5.0,<10.0.0)
Requires-Dist: httpx (>=0.23.0,<0.24.0)
Requires-Dist: loguru (>=0.6.0,<0.7.0)
Requires-Dist: psutil (>=5.9.1,<6.0.0)
Requires-Dist: pydantic (>=1.9.2,<2.0.0)
Requires-Dist: sh (>=1.14.3,<2.0.0)
Requires-Dist: typer (>=0.6.1,<0.7.0)
Project-URL: Repository, https://github.com/ninoseki/pycomponents
